aioice/__init__.py
aioice/candidate.py
aioice/ice.py
aioice/mdns.py
aioice/py.typed
aioice/stun.py
aioice/turn.py
aioice/utils.py
aioice_dimos-0.9.0.dist-info/licenses/LICENSE
aioice_dimos-0.9.0.dist-info/METADATA
aioice_dimos-0.9.0.dist-info/WHEEL
aioice_dimos-0.9.0.dist-info/top_level.txt
aioice_dimos-0.9.0.dist-info/RECORD
