Metadata-Version: 2.4
Name: aioice-dimos
Version: 0.9.0
Summary: An implementation of Interactive Connectivity Establishment (RFC 5245)
Author-email: Jeremy Lainé <jeremy.laine@m4x.org>
License: BSD-3-Clause
Project-URL: homepage, https://github.com/aiortc/aioice
Project-URL: documentation, https://aioice.readthedocs.io/
Classifier: Development Status :: 5 - Production/Stable
Classifier: Environment :: Web Environment
Classifier: Intended Audience :: Developers
Classifier: License :: OSI Approved :: BSD License
Classifier: Operating System :: OS Independent
Classifier: Programming Language :: Python
Classifier: Programming Language :: Python :: 3
Classifier: Programming Language :: Python :: 3.7
Classifier: Programming Language :: Python :: 3.8
Classifier: Programming Language :: Python :: 3.9
Classifier: Programming Language :: Python :: 3.10
Classifier: Programming Language :: Python :: 3.11
Requires-Python: >=3.7
License-File: LICENSE
Requires-Dist: dnspython>=2.0.0
Requires-Dist: ifaddr>=0.2.0
Provides-Extra: dev
Requires-Dist: coverage[toml]>=7.2.2; extra == "dev"
Dynamic: license-file
